[
    {
        "Message":  "Отсутствует \u0027\u0027)\u0027\u0027 в списке параметров функции.",
        "Content":  null
    },
    {
        "Message":  "Отсутствует закрывающий знак \"}\" в блоке операторов или определении типа.",
        "Content":  null
    },
    {
        "Message":  "Непредвиденная лексема \")\" в выражении или операторе.",
        "Content":  null
    },
    {
        "Message":  "Непредвиденная лексема \"}\" в выражении или операторе.",
        "Content":  null
    }
]
